setup.py
su99yday/__init__.py
su99yday/sunnyday.py
su99yday.egg-info/PKG-INFO
su99yday.egg-info/SOURCES.txt
su99yday.egg-info/dependency_links.txt
su99yday.egg-info/requires.txt
su99yday.egg-info/top_level.txt