Metadata-Version: 2.1
Name: su99yday
Version: 2.0.0
Summary: Weather forecast data
Home-page: https://example.com
Author: Bill Johnson
Author-email: bagpiper10044@yahoo.com
License: MIT
Keywords: weather,forecast,openweather
Classifier: Development Status :: 3 - Alpha
Classifier: Intended Audience :: Developers
Classifier: Topic :: Software Development :: Build Tools
Classifier: License :: OSI Approved :: MIT License
Classifier: Programming Language :: Python :: 3.5
Classifier: Programming Language :: Python :: 3.6
Classifier: Programming Language :: Python :: 3.7
Classifier: Programming Language :: Python :: 3.8
Classifier: Programming Language :: Python :: 3.9
Classifier: Programming Language :: Python :: 3.10
Classifier: Programming Language :: Python :: 3.11
